Metadata-Version: 1.0
Name: find-same
Version: 0.0
Summary: task for the first laboratory work
Home-page: UNKNOWN
Author: UNKNOWN
Author-email: ilya.t340508@gmail.com
License: UNKNOWN
Platform: UNKNOWN
